google/type/postal_address_pb2.py
google/type/postal_address_pb2_grpc.py
upollo/__init__.py
upollo/upollo.py
upollo/upollo_historian_pb2.py
upollo/upollo_historian_pb2_grpc.py
upollo/upollo_public_pb2.py
upollo/upollo_shadow_pb2.py
upollo/upollo_shepherd_pb2.py
upollo/upollo_shepherd_pb2_grpc.py
upollo_python-0.1.1.dist-info/LICENSE.md
upollo_python-0.1.1.dist-info/METADATA
upollo_python-0.1.1.dist-info/WHEEL
upollo_python-0.1.1.dist-info/top_level.txt
upollo_python-0.1.1.dist-info/RECORD
