Metadata-Version: 2.1
Name: upollo-python
Version: 0.1.1
Author: Upollo
Classifier: Programming Language :: Python :: 3
Classifier: License :: OSI Approved :: Apache Software License
Classifier: Operating System :: OS Independent
Requires-Python: >=3.7
License-File: LICENSE.md
Requires-Dist: grpcio (>=1.30)
Requires-Dist: protobuf (>=4.0)
